setup.py
Z21_onl/Lesson1.py
Z21_onl/Lesson10.py
Z21_onl/Lesson11.py
Z21_onl/Lesson2.py
Z21_onl/Lesson3.py
Z21_onl/Lesson4.py
Z21_onl/Lesson6.py
Z21_onl/Lesson8.py
Z21_onl/Lesson9.py
Z21_onl/Lessoon5.py
Z21_onl/__init__.py
Z21_onl.egg-info/PKG-INFO
Z21_onl.egg-info/SOURCES.txt
Z21_onl.egg-info/dependency_links.txt
Z21_onl.egg-info/requires.txt
Z21_onl.egg-info/top_level.txt