Metadata-Version: 2.1
Name: Z21-onl
Version: 0.15
Summary: Homework vers. 0. 15 includes all previous Homeworks
Home-page: https://z21-onl.com/
License: UNKNOWN
Platform: UNKNOWN
